[
    {
        "name": "MODEL NUMBERS",
        "link": "https://onlinemicrofiche.com/riva_normal/showmodel/13/seadoopwc/492/1",
        "full_name": "2015 Sea Doo PWC SAR 155 WHITE/YELLOW - MODEL NUMBERS",
        "image_src": "https://images.imagessite.com/OEM_IMAGES/seadoo_images_small/SD1584EA01.gif",
        "nameChildren": "MODEL NUMBERS",
        "breadcrumb_menu": "Sea Doo /  PWC  /  2015",
        "model": "2015 SAR 155 WHITE/YELLOW",
        "infor": [
            {
                "parts_list_HLSM_PartNo": null,
                "parts_list_PartNo": null,
                "parts_list_PartNo_RefNo": null,
                "parts_list_RefNo": "1",
                "parts_list_descrip": "84EASAR 155 WHITE/YELLOW NORTH AMERICA (CU)-ENGINE 1503 NA ITC (LFI)",
                "parts_list_SalePrice": "",
                "parts_list_QtyReq": "-",
                "image_main": "https://images.imagessite.com/OEM_IMAGES/seadoo_images/SD1584EA01.gif"
            }
        ]
    },
    {
        "name": "ELECTRICAL - BATTERY HARNESS",
        "link": "https://onlinemicrofiche.com/riva_normal/showmodel/13/seadoopwc/492/8",
        "full_name": "2015 Sea Doo PWC SAR 155 WHITE/YELLOW - ELECTRICAL - BATTERY HARNESS",
        "image_src": "https://images.imagessite.com/OEM_IMAGES/seadoo_images_small/SD1584EA08.gif",
        "nameChildren": "ELECTRICAL - BATTERY HARNESS",
        "breadcrumb_menu": "Sea Doo /  PWC  /  2015",
        "model": "2015 SAR 155 WHITE/YELLOW",
        "infor": [
            {
                "parts_list_HLSM_PartNo": "10967582",
                "parts_list_PartNo": "211000106",
                "parts_list_PartNo_RefNo": "2",
                "parts_list_RefNo": "2",
                "parts_list_descrip": "211000106HEX. FORMING SCREW M6 X 16",
                "parts_list_SalePrice": "1.99",
                "parts_list_QtyReq": "2",
                "image_main": "https://images.imagessite.com/OEM_IMAGES/seadoo_images/SD1584EA08.gif"
            },
            {
                "parts_list_HLSM_PartNo": "109623878",
                "parts_list_PartNo": "278003110",
                "parts_list_PartNo_RefNo": "13",
                "parts_list_RefNo": "13",
                "parts_list_descrip": "278003110POSITION LIGHT",
                "parts_list_SalePrice": "0.00",
                "parts_list_QtyReq": "1",
                "image_main": "https://images.imagessite.com/OEM_IMAGES/seadoo_images/SD1584EA08.gif"
            },
            {
                "parts_list_HLSM_PartNo": "109623879",
                "parts_list_PartNo": "278003112",
                "parts_list_PartNo_RefNo": "15",
                "parts_list_RefNo": "15",
                "parts_list_descrip": "278003112SECONDARY HARNESS",
                "parts_list_SalePrice": "449.99",
                "parts_list_QtyReq": "1",
                "image_main": "https://images.imagessite.com/OEM_IMAGES/seadoo_images/SD1584EA08.gif"
            },
            {
                "parts_list_HLSM_PartNo": "109623885",
                "parts_list_PartNo": "278003182",
                "parts_list_PartNo_RefNo": "17",
                "parts_list_RefNo": "17",
                "parts_list_descrip": "278003182LAMPE 360 ASSEMBLY",
                "parts_list_SalePrice": "349.99",
                "parts_list_QtyReq": "1",
                "image_main": "https://images.imagessite.com/OEM_IMAGES/seadoo_images/SD1584EA08.gif"
            },
            {
                "parts_list_HLSM_PartNo": "109628276",
                "parts_list_PartNo": "291002952",
                "parts_list_PartNo_RefNo": "19",
                "parts_list_RefNo": "19",
                "parts_list_descrip": "291002952HOSE BILGEFLEX",
                "parts_list_SalePrice": "8.29",
                "parts_list_QtyReq": "1",
                "image_main": "https://images.imagessite.com/OEM_IMAGES/seadoo_images/SD1584EA08.gif"
            },
            {
                "parts_list_HLSM_PartNo": "109629836",
                "parts_list_PartNo": "292001486",
                "parts_list_PartNo_RefNo": "21",
                "parts_list_RefNo": "21",
                "parts_list_descrip": "292001486GASKET",
                "parts_list_SalePrice": "6.09",
                "parts_list_QtyReq": "1",
                "image_main": "https://images.imagessite.com/OEM_IMAGES/seadoo_images/SD1584EA08.gif"
            },
            {
                "parts_list_HLSM_PartNo": "109630709",
                "parts_list_PartNo": "293650172",
                "parts_list_PartNo_RefNo": "22",
                "parts_list_RefNo": "22",
                "parts_list_descrip": "293650172TRIDON GEAR CLAMP",
                "parts_list_SalePrice": "2.99",
                "parts_list_QtyReq": "2",
                "image_main": "https://images.imagessite.com/OEM_IMAGES/seadoo_images/SD1584EA08.gif"
            },
            {
                "parts_list_HLSM_PartNo": "109630785",
                "parts_list_PartNo": "293710015",
                "parts_list_PartNo_RefNo": "23",
                "parts_list_RefNo": "23",
                "parts_list_descrip": "293710015PERKO FITTING 3/4\"",
                "parts_list_SalePrice": "12.99",
                "parts_list_QtyReq": "1",
                "image_main": "https://images.imagessite.com/OEM_IMAGES/seadoo_images/SD1584EA08.gif"
            },
            {
                "parts_list_HLSM_PartNo": "109630910",
                "parts_list_PartNo": "293720079",
                "parts_list_PartNo_RefNo": "24",
                "parts_list_RefNo": "24",
                "parts_list_descrip": "293720079CABLE GROMMET",
                "parts_list_SalePrice": "8.39",
                "parts_list_QtyReq": "1",
                "image_main": "https://images.imagessite.com/OEM_IMAGES/seadoo_images/SD1584EA08.gif"
            },
            {
                "parts_list_HLSM_PartNo": "109631749",
                "parts_list_PartNo": "295100597",
                "parts_list_PartNo_RefNo": "27",
                "parts_list_RefNo": "27",
                "parts_list_descrip": "295100597BILGE PUMP",
                "parts_list_SalePrice": "174.99",
                "parts_list_QtyReq": "1",
                "image_main": "https://images.imagessite.com/OEM_IMAGES/seadoo_images/SD1584EA08.gif"
            },
            {
                "parts_list_HLSM_PartNo": "109634829",
                "parts_list_PartNo": "414115200",
                "parts_list_PartNo_RefNo": "28",
                "parts_list_RefNo": "28",
                "parts_list_descrip": "414115200TIE-RAP 180 MM",
                "parts_list_SalePrice": "0.10",
                "parts_list_QtyReq": "@",
                "image_main": "https://images.imagessite.com/OEM_IMAGES/seadoo_images/SD1584EA08.gif"
            }
        ]
    },
    {
        "name": "COOLING SYSTEM",
        "link": "https://onlinemicrofiche.com/riva_normal/showmodel/13/seadoopwc/492/2",
        "full_name": "2015 Sea Doo PWC SAR 155 WHITE/YELLOW - COOLING SYSTEM",
        "image_src": "https://images.imagessite.com/OEM_IMAGES/seadoo_images_small/SD1584EA02.gif",
        "nameChildren": "COOLING SYSTEM",
        "breadcrumb_menu": "Sea Doo /  PWC  /  2015",
        "model": "2015 SAR 155 WHITE/YELLOW",
        "infor": [
            {
                "parts_list_HLSM_PartNo": "109620874",
                "parts_list_PartNo": "276000099",
                "parts_list_PartNo_RefNo": "4",
                "parts_list_RefNo": "4",
                "parts_list_descrip": "276000099HOSE 19 MM",
                "parts_list_SalePrice": "0.00",
                "parts_list_QtyReq": "@",
                "image_main": "https://images.imagessite.com/OEM_IMAGES/seadoo_images/SD1584EA02.gif"
            },
            {
                "parts_list_HLSM_PartNo": "109634781",
                "parts_list_PartNo": "409902200",
                "parts_list_PartNo_RefNo": "6",
                "parts_list_RefNo": "6",
                "parts_list_descrip": "409902200TUBING 25 MM",
                "parts_list_SalePrice": "0.00",
                "parts_list_QtyReq": "1",
                "image_main": "https://images.imagessite.com/OEM_IMAGES/seadoo_images/SD1584EA02.gif"
            },
            {
                "parts_list_HLSM_PartNo": "109620968",
                "parts_list_PartNo": "276000345",
                "parts_list_PartNo_RefNo": "7",
                "parts_list_RefNo": "7",
                "parts_list_descrip": "276000345HEAT EXCHANGER",
                "parts_list_SalePrice": "1,039.99",
                "parts_list_QtyReq": "1",
                "image_main": "https://images.imagessite.com/OEM_IMAGES/seadoo_images/SD1584EA02.gif"
            },
            {
                "parts_list_HLSM_PartNo": "109620969",
                "parts_list_PartNo": "276000350",
                "parts_list_PartNo_RefNo": "8",
                "parts_list_RefNo": "8",
                "parts_list_descrip": "276000350HOSE",
                "parts_list_SalePrice": "55.99",
                "parts_list_QtyReq": "1",
                "image_main": "https://images.imagessite.com/OEM_IMAGES/seadoo_images/SD1584EA02.gif"
            },
            {
                "parts_list_HLSM_PartNo": "109620970",
                "parts_list_PartNo": "276000351",
                "parts_list_PartNo_RefNo": "9",
                "parts_list_RefNo": "9",
                "parts_list_descrip": "276000351HOSE",
                "parts_list_SalePrice": "55.99",
                "parts_list_QtyReq": "1",
                "image_main": "https://images.imagessite.com/OEM_IMAGES/seadoo_images/SD1584EA02.gif"
            },
            {
                "parts_list_HLSM_PartNo": "109620971",
                "parts_list_PartNo": "276000353",
                "parts_list_PartNo_RefNo": "10",
                "parts_list_RefNo": "10",
                "parts_list_descrip": "276000353HOSE",
                "parts_list_SalePrice": "55.99",
                "parts_list_QtyReq": "1",
                "image_main": "https://images.imagessite.com/OEM_IMAGES/seadoo_images/SD1584EA02.gif"
            },
            {
                "parts_list_HLSM_PartNo": "109620981",
                "parts_list_PartNo": "276000368",
                "parts_list_PartNo_RefNo": "12",
                "parts_list_RefNo": "12",
                "parts_list_descrip": "276000368COOLING HOSE",
                "parts_list_SalePrice": "0.00",
                "parts_list_QtyReq": "1",
                "image_main": "https://images.imagessite.com/OEM_IMAGES/seadoo_images/SD1584EA02.gif"
            },
            {
                "parts_list_HLSM_PartNo": "109630646",
                "parts_list_PartNo": "293650045",
                "parts_list_PartNo_RefNo": "16",
                "parts_list_RefNo": "16",
                "parts_list_descrip": "293650045TRIDON GEAR CLAMP",
                "parts_list_SalePrice": "5.49",
                "parts_list_QtyReq": "2",
                "image_main": "https://images.imagessite.com/OEM_IMAGES/seadoo_images/SD1584EA02.gif"
            },
            {
                "parts_list_HLSM_PartNo": "109630714",
                "parts_list_PartNo": "293650185",
                "parts_list_PartNo_RefNo": "17",
                "parts_list_RefNo": "17",
                "parts_list_descrip": "293650185TRIDON GEAR CLAMP",
                "parts_list_SalePrice": "13.49",
                "parts_list_QtyReq": "2",
                "image_main": "https://images.imagessite.com/OEM_IMAGES/seadoo_images/SD1584EA02.gif"
            },
            {
                "parts_list_HLSM_PartNo": "109630714",
                "parts_list_PartNo": "293650185",
                "parts_list_PartNo_RefNo": "19",
                "parts_list_RefNo": "19",
                "parts_list_descrip": "293650185TRIDON GEAR CLAMP",
                "parts_list_SalePrice": "13.49",
                "parts_list_QtyReq": "2",
                "image_main": "https://images.imagessite.com/OEM_IMAGES/seadoo_images/SD1584EA02.gif"
            },
            {
                "parts_list_HLSM_PartNo": "109630651",
                "parts_list_PartNo": "293650051",
                "parts_list_PartNo_RefNo": "22",
                "parts_list_RefNo": "22",
                "parts_list_descrip": "293650051TRIDON GEAR CLAMP",
                "parts_list_SalePrice": "4.19",
                "parts_list_QtyReq": "1",
                "image_main": "https://images.imagessite.com/OEM_IMAGES/seadoo_images/SD1584EA02.gif"
            },
            {
                "parts_list_HLSM_PartNo": "109630651",
                "parts_list_PartNo": "293650051",
                "parts_list_PartNo_RefNo": "23",
                "parts_list_RefNo": "23",
                "parts_list_descrip": "293650051TRIDON GEAR CLAMP",
                "parts_list_SalePrice": "4.19",
                "parts_list_QtyReq": "3",
                "image_main": "https://images.imagessite.com/OEM_IMAGES/seadoo_images/SD1584EA02.gif"
            },
            {
                "parts_list_HLSM_PartNo": "109630776",
                "parts_list_PartNo": "293700052",
                "parts_list_PartNo_RefNo": "25",
                "parts_list_RefNo": "25",
                "parts_list_descrip": "293700052FEMALE FITTING",
                "parts_list_SalePrice": "32.99",
                "parts_list_QtyReq": "2",
                "image_main": "https://images.imagessite.com/OEM_IMAGES/seadoo_images/SD1584EA02.gif"
            },
            {
                "parts_list_HLSM_PartNo": "109630777",
                "parts_list_PartNo": "293700053",
                "parts_list_PartNo_RefNo": "26",
                "parts_list_RefNo": "26",
                "parts_list_descrip": "293700053REDUCER 1-3/4\" NPT",
                "parts_list_SalePrice": "0.00",
                "parts_list_QtyReq": "2",
                "image_main": "https://images.imagessite.com/OEM_IMAGES/seadoo_images/SD1584EA02.gif"
            },
            {
                "parts_list_HLSM_PartNo": "109630778",
                "parts_list_PartNo": "293700054",
                "parts_list_PartNo_RefNo": "28",
                "parts_list_RefNo": "28",
                "parts_list_descrip": "293700054MALE FITTING 3/4\" NPT",
                "parts_list_SalePrice": "18.49",
                "parts_list_QtyReq": "2",
                "image_main": "https://images.imagessite.com/OEM_IMAGES/seadoo_images/SD1584EA02.gif"
            },
            {
                "parts_list_HLSM_PartNo": "109630959",
                "parts_list_PartNo": "293750008",
                "parts_list_PartNo_RefNo": "30",
                "parts_list_RefNo": "30",
                "parts_list_descrip": "293750008TIE-RAP 350 MM",
                "parts_list_SalePrice": "0.98",
                "parts_list_QtyReq": "1",
                "image_main": "https://images.imagessite.com/OEM_IMAGES/seadoo_images/SD1584EA02.gif"
            },
            {
                "parts_list_HLSM_PartNo": "109639224",
                "parts_list_PartNo": "515176044",
                "parts_list_PartNo_RefNo": "35",
                "parts_list_RefNo": "35",
                "parts_list_descrip": "515176044BATTERY STRAP",
                "parts_list_SalePrice": "16.99",
                "parts_list_QtyReq": "2",
                "image_main": "https://images.imagessite.com/OEM_IMAGES/seadoo_images/SD1584EA02.gif"
            }
        ]
    },
    {
        "name": "PROPULSION SYSTEM - EXTERNAL",
        "link": "https://onlinemicrofiche.com/riva_normal/showmodel/13/seadoopwc/492/4",
        "full_name": "2015 Sea Doo PWC SAR 155 WHITE/YELLOW - PROPULSION SYSTEM - EXTERNAL",
        "image_src": "https://images.imagessite.com/OEM_IMAGES/seadoo_images_small/SD1584EA04.gif",
        "nameChildren": "PROPULSION SYSTEM - EXTERNAL",
        "breadcrumb_menu": "Sea Doo /  PWC  /  2015",
        "model": "2015 SAR 155 WHITE/YELLOW",
        "infor": [
            {
                "parts_list_HLSM_PartNo": "109614332",
                "parts_list_PartNo": "267000540",
                "parts_list_PartNo_RefNo": "1",
                "parts_list_RefNo": "1",
                "parts_list_descrip": "267000540IMPELLER HOUSING",
                "parts_list_SalePrice": "309.99",
                "parts_list_QtyReq": "1",
                "image_main": "https://images.imagessite.com/OEM_IMAGES/seadoo_images/SD1584EA04.gif"
            },
            {
                "parts_list_HLSM_PartNo": "109614427",
                "parts_list_PartNo": "267000800",
                "parts_list_PartNo_RefNo": "2",
                "parts_list_RefNo": "2",
                "parts_list_descrip": "267000800WEAR RING",
                "parts_list_SalePrice": "359.99",
                "parts_list_QtyReq": "1",
                "image_main": "https://images.imagessite.com/OEM_IMAGES/seadoo_images/SD1584EA04.gif"
            }
        ]
    },
    {
        "name": "PROPULSION SYSTEM - INTERNAL",
        "link": "https://onlinemicrofiche.com/riva_normal/showmodel/13/seadoopwc/492/3",
        "full_name": "2015 Sea Doo PWC SAR 155 WHITE/YELLOW - PROPULSION SYSTEM - INTERNAL",
        "image_src": "https://images.imagessite.com/OEM_IMAGES/seadoo_images_small/SD1584EA03.gif",
        "nameChildren": "PROPULSION SYSTEM - INTERNAL",
        "breadcrumb_menu": "Sea Doo /  PWC  /  2015",
        "model": "2015 SAR 155 WHITE/YELLOW",
        "infor": [
            {
                "parts_list_HLSM_PartNo": "10967140",
                "parts_list_PartNo": "207381660",
                "parts_list_PartNo_RefNo": "1",
                "parts_list_RefNo": "1",
                "parts_list_descrip": "207381660HEX. SCREW M8 X 16, SCOTCH GRIP",
                "parts_list_SalePrice": "0.95",
                "parts_list_QtyReq": "3",
                "image_main": "https://images.imagessite.com/OEM_IMAGES/seadoo_images/SD1584EA03.gif"
            },
            {
                "parts_list_HLSM_PartNo": "109612934",
                "parts_list_PartNo": "234081600",
                "parts_list_PartNo_RefNo": "2",
                "parts_list_RefNo": "2",
                "parts_list_descrip": "234081600FLAT WASHER 8 MM, STAINLESS",
                "parts_list_SalePrice": "0.52",
                "parts_list_QtyReq": "3",
                "image_main": "https://images.imagessite.com/OEM_IMAGES/seadoo_images/SD1584EA03.gif"
            },
            {
                "parts_list_HLSM_PartNo": "109613295",
                "parts_list_PartNo": "250000530",
                "parts_list_PartNo_RefNo": "3",
                "parts_list_RefNo": "3",
                "parts_list_descrip": "250000530HEX. SCREW M8 X 40, SCOTCH GRIP",
                "parts_list_SalePrice": "1.89",
                "parts_list_QtyReq": "1",
                "image_main": "https://images.imagessite.com/OEM_IMAGES/seadoo_images/SD1584EA03.gif"
            },
            {
                "parts_list_HLSM_PartNo": "109619415",
                "parts_list_PartNo": "271001948",
                "parts_list_PartNo_RefNo": "4",
                "parts_list_RefNo": "4",
                "parts_list_descrip": "271001948PUMP GRATE",
                "parts_list_SalePrice": "114.99",
                "parts_list_QtyReq": "1",
                "image_main": "https://images.imagessite.com/OEM_IMAGES/seadoo_images/SD1584EA03.gif"
            },
            {
                "parts_list_HLSM_PartNo": "109630087",
                "parts_list_PartNo": "293050001",
                "parts_list_PartNo_RefNo": "6",
                "parts_list_RefNo": "6",
                "parts_list_descrip": "293050001FLAT WASHER",
                "parts_list_SalePrice": "2.89",
                "parts_list_QtyReq": "1",
                "image_main": "https://images.imagessite.com/OEM_IMAGES/seadoo_images/SD1584EA03.gif"
            },
            {
                "parts_list_HLSM_PartNo": "109631047",
                "parts_list_PartNo": "293830047",
                "parts_list_PartNo_RefNo": "8",
                "parts_list_RefNo": "8",
                "parts_list_descrip": "293830047PROTECTOR DISK",
                "parts_list_SalePrice": "1.99",
                "parts_list_QtyReq": "1",
                "image_main": "https://images.imagessite.com/OEM_IMAGES/seadoo_images/SD1584EA03.gif"
            }
        ]
    },
    {
        "name": "BODY - DECK VIEW",
        "link": "https://onlinemicrofiche.com/riva_normal/showmodel/13/seadoopwc/492/5",
        "full_name": "2015 Sea Doo PWC SAR 155 WHITE/YELLOW - BODY - DECK VIEW",
        "image_src": "https://images.imagessite.com/OEM_IMAGES/seadoo_images_small/SD1584EA05.gif",
        "nameChildren": "BODY - DECK VIEW",
        "breadcrumb_menu": "Sea Doo /  PWC  /  2015",
        "model": "2015 SAR 155 WHITE/YELLOW",
        "infor": [
            {
                "parts_list_HLSM_PartNo": "10966775",
                "parts_list_PartNo": "205062560",
                "parts_list_PartNo_RefNo": "1",
                "parts_list_RefNo": "1",
                "parts_list_descrip": "205062560SOCKET HEAD SCREW M6 X 25",
                "parts_list_SalePrice": "1.59",
                "parts_list_QtyReq": "8",
                "image_main": "https://images.imagessite.com/OEM_IMAGES/seadoo_images/SD1584EA05.gif"
            },
            {
                "parts_list_HLSM_PartNo": "10966896",
                "parts_list_PartNo": "205561660",
                "parts_list_PartNo_RefNo": "2",
                "parts_list_RefNo": "2",
                "parts_list_descrip": "205561660SOCKET HEAD SCREW M6 X 16, SCOTCH GRIP",
                "parts_list_SalePrice": "1.59",
                "parts_list_QtyReq": "6",
                "image_main": "https://images.imagessite.com/OEM_IMAGES/seadoo_images/SD1584EA05.gif"
            },
            {
                "parts_list_HLSM_PartNo": "10966903",
                "parts_list_PartNo": "205566060",
                "parts_list_PartNo_RefNo": "3",
                "parts_list_RefNo": "3",
                "parts_list_descrip": "205566060SOCKET HEAD SCREW",
                "parts_list_SalePrice": "6.09",
                "parts_list_QtyReq": "8",
                "image_main": "https://images.imagessite.com/OEM_IMAGES/seadoo_images/SD1584EA05.gif"
            },
            {
                "parts_list_HLSM_PartNo": "10966984",
                "parts_list_PartNo": "207065560",
                "parts_list_PartNo_RefNo": "4",
                "parts_list_RefNo": "4",
                "parts_list_descrip": "207065560HEX. SCREW M6 X 55",
                "parts_list_SalePrice": "0.95",
                "parts_list_QtyReq": "2",
                "image_main": "https://images.imagessite.com/OEM_IMAGES/seadoo_images/SD1584EA05.gif"
            },
            {
                "parts_list_HLSM_PartNo": "10967078",
                "parts_list_PartNo": "207164060",
                "parts_list_PartNo_RefNo": "5",
                "parts_list_RefNo": "5",
                "parts_list_descrip": "207164060HEX. SCREW M6 X 40",
                "parts_list_SalePrice": "3.19",
                "parts_list_QtyReq": "4",
                "image_main": "https://images.imagessite.com/OEM_IMAGES/seadoo_images/SD1584EA05.gif"
            },
            {
                "parts_list_HLSM_PartNo": "10967527",
                "parts_list_PartNo": "211000023",
                "parts_list_PartNo_RefNo": "6",
                "parts_list_RefNo": "6",
                "parts_list_descrip": "211000023HEX. SCREW 10-14 X 7/8??",
                "parts_list_SalePrice": "3.39",
                "parts_list_QtyReq": "4",
                "image_main": "https://images.imagessite.com/OEM_IMAGES/seadoo_images/SD1584EA05.gif"
            },
            {
                "parts_list_HLSM_PartNo": "109612784",
                "parts_list_PartNo": "232100600",
                "parts_list_PartNo_RefNo": "7",
                "parts_list_RefNo": "7",
                "parts_list_descrip": "232100600HEX. JAM NUT M10",
                "parts_list_SalePrice": "2.09",
                "parts_list_QtyReq": "1",
                "image_main": "https://images.imagessite.com/OEM_IMAGES/seadoo_images/SD1584EA05.gif"
            },
            {
                "parts_list_HLSM_PartNo": "109612801",
                "parts_list_PartNo": "232361600",
                "parts_list_PartNo_RefNo": "8",
                "parts_list_RefNo": "8",
                "parts_list_descrip": "232361600NUT M6",
                "parts_list_SalePrice": "4.09",
                "parts_list_QtyReq": "8",
                "image_main": "https://images.imagessite.com/OEM_IMAGES/seadoo_images/SD1584EA05.gif"
            },
            {
                "parts_list_HLSM_PartNo": "109612805",
                "parts_list_PartNo": "232501200",
                "parts_list_PartNo_RefNo": "9",
                "parts_list_RefNo": "9",
                "parts_list_descrip": "232501200ELASTIC STOP NUT M10, BRASS",
                "parts_list_SalePrice": "2.69",
                "parts_list_QtyReq": "1",
                "image_main": "https://images.imagessite.com/OEM_IMAGES/seadoo_images/SD1584EA05.gif"
            },
            {
                "parts_list_HLSM_PartNo": "109612823",
                "parts_list_PartNo": "232561200",
                "parts_list_PartNo_RefNo": "10",
                "parts_list_RefNo": "10",
                "parts_list_descrip": "232561200ELASTIC STOP NUT M6, BRASS",
                "parts_list_SalePrice": "3.99",
                "parts_list_QtyReq": "@",
                "image_main": "https://images.imagessite.com/OEM_IMAGES/seadoo_images/SD1584EA05.gif"
            },
            {
                "parts_list_HLSM_PartNo": "109612830",
                "parts_list_PartNo": "232581200",
                "parts_list_PartNo_RefNo": "11",
                "parts_list_RefNo": "11",
                "parts_list_descrip": "232581200HEX. ELASTIC NUT M8, BRASS",
                "parts_list_SalePrice": "2.09",
                "parts_list_QtyReq": "2",
                "image_main": "https://images.imagessite.com/OEM_IMAGES/seadoo_images/SD1584EA05.gif"
            },
            {
                "parts_list_HLSM_PartNo": "109612899",
                "parts_list_PartNo": "234002600",
                "parts_list_PartNo_RefNo": "12",
                "parts_list_RefNo": "12",
                "parts_list_descrip": "234002600FLAT WASHER 10 MM, STAINLESS",
                "parts_list_SalePrice": "2.09",
                "parts_list_QtyReq": "1",
                "image_main": "https://images.imagessite.com/OEM_IMAGES/seadoo_images/SD1584EA05.gif"
            },
            {
                "parts_list_HLSM_PartNo": "109612923",
                "parts_list_PartNo": "234061600",
                "parts_list_PartNo_RefNo": "13",
                "parts_list_RefNo": "13",
                "parts_list_descrip": "234061600FLAT WASHER M6, STAINLESS",
                "parts_list_SalePrice": "0.31",
                "parts_list_QtyReq": "6",
                "image_main": "https://images.imagessite.com/OEM_IMAGES/seadoo_images/SD1584EA05.gif"
            },
            {
                "parts_list_HLSM_PartNo": "109612928",
                "parts_list_PartNo": "234062600",
                "parts_list_PartNo_RefNo": "14",
                "parts_list_RefNo": "14",
                "parts_list_descrip": "234062600FLAT WASHER M6, STAINLESS",
                "parts_list_SalePrice": "0.73",
                "parts_list_QtyReq": "@",
                "image_main": "https://images.imagessite.com/OEM_IMAGES/seadoo_images/SD1584EA05.gif"
            },
            {
                "parts_list_HLSM_PartNo": "109612929",
                "parts_list_PartNo": "234062670",
                "parts_list_PartNo_RefNo": "15",
                "parts_list_RefNo": "15",
                "parts_list_descrip": "234062670FLAT WASHER, STAINLESS",
                "parts_list_SalePrice": "1.99",
                "parts_list_QtyReq": "8",
                "image_main": "https://images.imagessite.com/OEM_IMAGES/seadoo_images/SD1584EA05.gif"
            },
            {
                "parts_list_HLSM_PartNo": "109612938",
                "parts_list_PartNo": "234082600",
                "parts_list_PartNo_RefNo": "16",
                "parts_list_RefNo": "16",
                "parts_list_descrip": "234082600FLAT WASHER 8 MM, STAINLESS",
                "parts_list_SalePrice": "2.29",
                "parts_list_QtyReq": "2",
                "image_main": "https://images.imagessite.com/OEM_IMAGES/seadoo_images/SD1584EA05.gif"
            },
            {
                "parts_list_HLSM_PartNo": "109613184",
                "parts_list_PartNo": "250000350",
                "parts_list_PartNo_RefNo": "17",
                "parts_list_RefNo": "17",
                "parts_list_descrip": "250000350TORX TRUSS SCREW M6 X 20",
                "parts_list_SalePrice": "4.99",
                "parts_list_QtyReq": "8",
                "image_main": "https://images.imagessite.com/OEM_IMAGES/seadoo_images/SD1584EA05.gif"
            },
            {
                "parts_list_HLSM_PartNo": "109613212",
                "parts_list_PartNo": "250000399",
                "parts_list_PartNo_RefNo": "18",
                "parts_list_RefNo": "18",
                "parts_list_descrip": "250000399HEXAGONAL CAP SCREW M6 X35",
                "parts_list_SalePrice": "4.19",
                "parts_list_QtyReq": "2",
                "image_main": "https://images.imagessite.com/OEM_IMAGES/seadoo_images/SD1584EA05.gif"
            },
            {
                "parts_list_HLSM_PartNo": "109613270",
                "parts_list_PartNo": "250000488",
                "parts_list_PartNo_RefNo": "19",
                "parts_list_RefNo": "19",
                "parts_list_descrip": "250000488TORX TRUSS SCREW M6 X 20",
                "parts_list_SalePrice": "1.99",
                "parts_list_QtyReq": "8",
                "image_main": "https://images.imagessite.com/OEM_IMAGES/seadoo_images/SD1584EA05.gif"
            },
            {
                "parts_list_HLSM_PartNo": "109613393",
                "parts_list_PartNo": "250000709",
                "parts_list_PartNo_RefNo": "20",
                "parts_list_RefNo": "20",
                "parts_list_descrip": "250000709TORX SCREW M6.81 X 30",
                "parts_list_SalePrice": "2.29",
                "parts_list_QtyReq": "4",
                "image_main": "https://images.imagessite.com/OEM_IMAGES/seadoo_images/SD1584EA05.gif"
            },
            {
                "parts_list_HLSM_PartNo": "109628889",
                "parts_list_PartNo": "291004284",
                "parts_list_PartNo_RefNo": "21",
                "parts_list_RefNo": "21",
                "parts_list_descrip": "291004284THREAD SCREW FILET 1/4-20 X 1 1/4",
                "parts_list_SalePrice": "2.39",
                "parts_list_QtyReq": "6",
                "image_main": "https://images.imagessite.com/OEM_IMAGES/seadoo_images/SD1584EA05.gif"
            },
            {
                "parts_list_HLSM_PartNo": "109613416",
                "parts_list_PartNo": "250000744",
                "parts_list_PartNo_RefNo": "22",
                "parts_list_RefNo": "22",
                "parts_list_descrip": "250000744TORX SCEW M6 X 30",
                "parts_list_SalePrice": "1.89",
                "parts_list_QtyReq": "@",
                "image_main": "https://images.imagessite.com/OEM_IMAGES/seadoo_images/SD1584EA05.gif"
            },
            {
                "parts_list_HLSM_PartNo": "109613804",
                "parts_list_PartNo": "250200022",
                "parts_list_PartNo_RefNo": "23",
                "parts_list_RefNo": "23",
                "parts_list_descrip": "250200022FLAT WASHER M6.6 X 22",
                "parts_list_SalePrice": "2.29",
                "parts_list_QtyReq": "4",
                "image_main": "https://images.imagessite.com/OEM_IMAGES/seadoo_images/SD1584EA05.gif"
            },
            {
                "parts_list_HLSM_PartNo": "109615637",
                "parts_list_PartNo": "269002125",
                "parts_list_PartNo_RefNo": "24",
                "parts_list_RefNo": "24",
                "parts_list_descrip": "269002125SEAT STUD SPACER",
                "parts_list_SalePrice": "7.29",
                "parts_list_QtyReq": "1",
                "image_main": "https://images.imagessite.com/OEM_IMAGES/seadoo_images/SD1584EA05.gif"
            },
            {
                "parts_list_HLSM_PartNo": "109615638",
                "parts_list_PartNo": "269002126",
                "parts_list_PartNo_RefNo": "25",
                "parts_list_RefNo": "25",
                "parts_list_descrip": "269002126SEAT STUD SUPPORT",
                "parts_list_SalePrice": "7.29",
                "parts_list_QtyReq": "1",
                "image_main": "https://images.imagessite.com/OEM_IMAGES/seadoo_images/SD1584EA05.gif"
            },
            {
                "parts_list_HLSM_PartNo": "109615978",
                "parts_list_PartNo": "269002769",
                "parts_list_PartNo_RefNo": "26",
                "parts_list_RefNo": "26",
                "parts_list_descrip": "269002769REAR HANDLE",
                "parts_list_SalePrice": "0.00",
                "parts_list_QtyReq": "1",
                "image_main": "https://images.imagessite.com/OEM_IMAGES/seadoo_images/SD1584EA05.gif"
            },
            {
                "parts_list_HLSM_PartNo": "109617115",
                "parts_list_PartNo": "269501812",
                "parts_list_PartNo_RefNo": "28",
                "parts_list_RefNo": "28",
                "parts_list_descrip": "269501812WHITE RH COSMETIC PANEL",
                "parts_list_SalePrice": "124.99",
                "parts_list_QtyReq": "1",
                "image_main": "https://images.imagessite.com/OEM_IMAGES/seadoo_images/SD1584EA05.gif"
            },
            {
                "parts_list_HLSM_PartNo": "109617116",
                "parts_list_PartNo": "269501813",
                "parts_list_PartNo_RefNo": "29",
                "parts_list_RefNo": "29",
                "parts_list_descrip": "269501813WHITE LH COSMETIC PANEL",
                "parts_list_SalePrice": "0.00",
                "parts_list_QtyReq": "1",
                "image_main": "https://images.imagessite.com/OEM_IMAGES/seadoo_images/SD1584EA05.gif"
            },
            {
                "parts_list_HLSM_PartNo": "109627604",
                "parts_list_PartNo": "291001386",
                "parts_list_PartNo_RefNo": "31",
                "parts_list_RefNo": "31",
                "parts_list_descrip": "291001386FINITION PLATE, BLACK",
                "parts_list_SalePrice": "9.69",
                "parts_list_QtyReq": "1",
                "image_main": "https://images.imagessite.com/OEM_IMAGES/seadoo_images/SD1584EA05.gif"
            },
            {
                "parts_list_HLSM_PartNo": "109628827",
                "parts_list_PartNo": "291004153",
                "parts_list_PartNo_RefNo": "32",
                "parts_list_RefNo": "32",
                "parts_list_descrip": "291004153RH BUMPER CORNER",
                "parts_list_SalePrice": "25.99",
                "parts_list_QtyReq": "1",
                "image_main": "https://images.imagessite.com/OEM_IMAGES/seadoo_images/SD1584EA05.gif"
            },
            {
                "parts_list_HLSM_PartNo": "109628826",
                "parts_list_PartNo": "291004152",
                "parts_list_PartNo_RefNo": "33",
                "parts_list_RefNo": "33",
                "parts_list_descrip": "291004152LH BUMPER CORNER",
                "parts_list_SalePrice": "25.99",
                "parts_list_QtyReq": "1",
                "image_main": "https://images.imagessite.com/OEM_IMAGES/seadoo_images/SD1584EA05.gif"
            },
            {
                "parts_list_HLSM_PartNo": "109628741",
                "parts_list_PartNo": "291003872",
                "parts_list_PartNo_RefNo": "34",
                "parts_list_RefNo": "34",
                "parts_list_descrip": "291003872LATERAL BUMPER",
                "parts_list_SalePrice": "119.99",
                "parts_list_QtyReq": "1",
                "image_main": "https://images.imagessite.com/OEM_IMAGES/seadoo_images/SD1584EA05.gif"
            },
            {
                "parts_list_HLSM_PartNo": "109628742",
                "parts_list_PartNo": "291003877",
                "parts_list_PartNo_RefNo": "35",
                "parts_list_RefNo": "35",
                "parts_list_descrip": "291003877STUD SEAT",
                "parts_list_SalePrice": "43.99",
                "parts_list_QtyReq": "1",
                "image_main": "https://images.imagessite.com/OEM_IMAGES/seadoo_images/SD1584EA05.gif"
            },
            {
                "parts_list_HLSM_PartNo": "109628767",
                "parts_list_PartNo": "291003955",
                "parts_list_PartNo_RefNo": "37",
                "parts_list_RefNo": "37",
                "parts_list_descrip": "291003955RH FLOAT INFLATABLE BALLOON",
                "parts_list_SalePrice": "0.00",
                "parts_list_QtyReq": "1",
                "image_main": "https://images.imagessite.com/OEM_IMAGES/seadoo_images/SD1584EA05.gif"
            },
            {
                "parts_list_HLSM_PartNo": "109628768",
                "parts_list_PartNo": "291003956",
                "parts_list_PartNo_RefNo": "45",
                "parts_list_RefNo": "45",
                "parts_list_descrip": "291003956LH FLOAT INFLATABLE BALLOON",
                "parts_list_SalePrice": "0.00",
                "parts_list_QtyReq": "1",
                "image_main": "https://images.imagessite.com/OEM_IMAGES/seadoo_images/SD1584EA05.gif"
            },
            {
                "parts_list_HLSM_PartNo": "109628897",
                "parts_list_PartNo": "291004294",
                "parts_list_PartNo_RefNo": "51",
                "parts_list_RefNo": "51",
                "parts_list_descrip": "291004294REAR BALLOON SLIDE RAIL",
                "parts_list_SalePrice": "109.99",
                "parts_list_QtyReq": "2",
                "image_main": "https://images.imagessite.com/OEM_IMAGES/seadoo_images/SD1584EA05.gif"
            },
            {
                "parts_list_HLSM_PartNo": "109628770",
                "parts_list_PartNo": "291003967",
                "parts_list_PartNo_RefNo": "53",
                "parts_list_RefNo": "53",
                "parts_list_descrip": "291003967RH UPPER SUPPORT",
                "parts_list_SalePrice": "109.99",
                "parts_list_QtyReq": "1",
                "image_main": "https://images.imagessite.com/OEM_IMAGES/seadoo_images/SD1584EA05.gif"
            },
            {
                "parts_list_HLSM_PartNo": "109628773",
                "parts_list_PartNo": "291003970",
                "parts_list_PartNo_RefNo": "54",
                "parts_list_RefNo": "54",
                "parts_list_descrip": "291003970MAST ASS'Y",
                "parts_list_SalePrice": "0.00",
                "parts_list_QtyReq": "1",
                "image_main": "https://images.imagessite.com/OEM_IMAGES/seadoo_images/SD1584EA05.gif"
            },
            {
                "parts_list_HLSM_PartNo": "109628773",
                "parts_list_PartNo": "291003970",
                "parts_list_PartNo_RefNo": "55",
                "parts_list_RefNo": "55",
                "parts_list_descrip": "291003970MAST ASS'Y",
                "parts_list_SalePrice": "0.00",
                "parts_list_QtyReq": "1",
                "image_main": "https://images.imagessite.com/OEM_IMAGES/seadoo_images/SD1584EA05.gif"
            },
            {
                "parts_list_HLSM_PartNo": "109628773",
                "parts_list_PartNo": "291003970",
                "parts_list_PartNo_RefNo": "56",
                "parts_list_RefNo": "56",
                "parts_list_descrip": "291003970MAST ASS'Y",
                "parts_list_SalePrice": "0.00",
                "parts_list_QtyReq": "1",
                "image_main": "https://images.imagessite.com/OEM_IMAGES/seadoo_images/SD1584EA05.gif"
            },
            {
                "parts_list_HLSM_PartNo": "109628773",
                "parts_list_PartNo": "291003970",
                "parts_list_PartNo_RefNo": "57",
                "parts_list_RefNo": "57",
                "parts_list_descrip": "291003970MAST ASS'Y",
                "parts_list_SalePrice": "0.00",
                "parts_list_QtyReq": "1",
                "image_main": "https://images.imagessite.com/OEM_IMAGES/seadoo_images/SD1584EA05.gif"
            },
            {
                "parts_list_HLSM_PartNo": "109628774",
                "parts_list_PartNo": "291003974",
                "parts_list_PartNo_RefNo": "58",
                "parts_list_RefNo": "58",
                "parts_list_descrip": "291003974LINK BAR SUPPORT ASSEMBLY",
                "parts_list_SalePrice": "419.99",
                "parts_list_QtyReq": "1",
                "image_main": "https://images.imagessite.com/OEM_IMAGES/seadoo_images/SD1584EA05.gif"
            },
            {
                "parts_list_HLSM_PartNo": "109628772",
                "parts_list_PartNo": "291003969",
                "parts_list_PartNo_RefNo": "58",
                "parts_list_RefNo": "58",
                "parts_list_descrip": "291003969ROD STOPPER BLOCK",
                "parts_list_SalePrice": "83.99",
                "parts_list_QtyReq": "1",
                "image_main": "https://images.imagessite.com/OEM_IMAGES/seadoo_images/SD1584EA05.gif"
            },
            {
                "parts_list_HLSM_PartNo": "109628775",
                "parts_list_PartNo": "291003979",
                "parts_list_PartNo_RefNo": "61",
                "parts_list_RefNo": "61",
                "parts_list_descrip": "291003979RH REAR FOOT PAD",
                "parts_list_SalePrice": "124.99",
                "parts_list_QtyReq": "1",
                "image_main": "https://images.imagessite.com/OEM_IMAGES/seadoo_images/SD1584EA05.gif"
            },
            {
                "parts_list_HLSM_PartNo": "109628776",
                "parts_list_PartNo": "291003980",
                "parts_list_PartNo_RefNo": "62",
                "parts_list_RefNo": "62",
                "parts_list_descrip": "291003980LH REAR FOOT PAD",
                "parts_list_SalePrice": "119.99",
                "parts_list_QtyReq": "1",
                "image_main": "https://images.imagessite.com/OEM_IMAGES/seadoo_images/SD1584EA05.gif"
            },
            {
                "parts_list_HLSM_PartNo": "109628783",
                "parts_list_PartNo": "291003989",
                "parts_list_PartNo_RefNo": "63",
                "parts_list_RefNo": "63",
                "parts_list_descrip": "291003989REAR BALLOON SUPPORT",
                "parts_list_SalePrice": "84.99",
                "parts_list_QtyReq": "2",
                "image_main": "https://images.imagessite.com/OEM_IMAGES/seadoo_images/SD1584EA05.gif"
            },
            {
                "parts_list_HLSM_PartNo": "109628795",
                "parts_list_PartNo": "291004051",
                "parts_list_PartNo_RefNo": "65",
                "parts_list_RefNo": "65",
                "parts_list_descrip": "291004051FRONT BALLOON SUPPORT",
                "parts_list_SalePrice": "109.99",
                "parts_list_QtyReq": "2",
                "image_main": "https://images.imagessite.com/OEM_IMAGES/seadoo_images/SD1584EA05.gif"
            },
            {
                "parts_list_HLSM_PartNo": null,
                "parts_list_PartNo": null,
                "parts_list_PartNo_RefNo": null,
                "parts_list_RefNo": "67",
                "parts_list_descrip": "291004054FOOT ANCHOR",
                "parts_list_SalePrice": "",
                "parts_list_QtyReq": "8",
                "image_main": "https://images.imagessite.com/OEM_IMAGES/seadoo_images/SD1584EA05.gif"
            },
            {
                "parts_list_HLSM_PartNo": "109628796",
                "parts_list_PartNo": "291004055",
                "parts_list_PartNo_RefNo": "68",
                "parts_list_RefNo": "68",
                "parts_list_descrip": "291004055FOOT SUPPORT",
                "parts_list_SalePrice": "189.99",
                "parts_list_QtyReq": "4",
                "image_main": "https://images.imagessite.com/OEM_IMAGES/seadoo_images/SD1584EA05.gif"
            },
            {
                "parts_list_HLSM_PartNo": null,
                "parts_list_PartNo": null,
                "parts_list_PartNo_RefNo": null,
                "parts_list_RefNo": "69",
                "parts_list_descrip": "291004057RUBBER STOPPER",
                "parts_list_SalePrice": "",
                "parts_list_QtyReq": "4",
                "image_main": "https://images.imagessite.com/OEM_IMAGES/seadoo_images/SD1584EA05.gif"
            },
            {
                "parts_list_HLSM_PartNo": "109628798",
                "parts_list_PartNo": "291004058",
                "parts_list_PartNo_RefNo": "70",
                "parts_list_RefNo": "70",
                "parts_list_descrip": "291004058FLOORBOARD MOUNTING PLATE",
                "parts_list_SalePrice": "78.99",
                "parts_list_QtyReq": "8",
                "image_main": "https://images.imagessite.com/OEM_IMAGES/seadoo_images/SD1584EA05.gif"
            },
            {
                "parts_list_HLSM_PartNo": "109628805",
                "parts_list_PartNo": "291004087",
                "parts_list_PartNo_RefNo": "71",
                "parts_list_RefNo": "71",
                "parts_list_descrip": "291004087RH COVER SUPPORT",
                "parts_list_SalePrice": "67.99",
                "parts_list_QtyReq": "1",
                "image_main": "https://images.imagessite.com/OEM_IMAGES/seadoo_images/SD1584EA05.gif"
            },
            {
                "parts_list_HLSM_PartNo": "109628806",
                "parts_list_PartNo": "291004088",
                "parts_list_PartNo_RefNo": "72",
                "parts_list_RefNo": "72",
                "parts_list_descrip": "291004088LH COVER SUPPORT",
                "parts_list_SalePrice": "0.00",
                "parts_list_QtyReq": "1",
                "image_main": "https://images.imagessite.com/OEM_IMAGES/seadoo_images/SD1584EA05.gif"
            },
            {
                "parts_list_HLSM_PartNo": "109628813",
                "parts_list_PartNo": "291004111",
                "parts_list_PartNo_RefNo": "73",
                "parts_list_RefNo": "73",
                "parts_list_descrip": "291004111BUMPER SUPPORT MA",
                "parts_list_SalePrice": "234.99",
                "parts_list_QtyReq": "1",
                "image_main": "https://images.imagessite.com/OEM_IMAGES/seadoo_images/SD1584EA05.gif"
            },
            {
                "parts_list_HLSM_PartNo": "109628831",
                "parts_list_PartNo": "291004162",
                "parts_list_PartNo_RefNo": "74",
                "parts_list_RefNo": "74",
                "parts_list_descrip": "291004162BUMPER WITH PROTECTIVE COATING",
                "parts_list_SalePrice": "0.00",
                "parts_list_QtyReq": "1",
                "image_main": "https://images.imagessite.com/OEM_IMAGES/seadoo_images/SD1584EA05.gif"
            },
            {
                "parts_list_HLSM_PartNo": "109628814",
                "parts_list_PartNo": "291004113",
                "parts_list_PartNo_RefNo": "75",
                "parts_list_RefNo": "75",
                "parts_list_descrip": "291004113RH FRONT FOOT PAD",
                "parts_list_SalePrice": "47.99",
                "parts_list_QtyReq": "1",
                "image_main": "https://images.imagessite.com/OEM_IMAGES/seadoo_images/SD1584EA05.gif"
            },
            {
                "parts_list_HLSM_PartNo": "109628815",
                "parts_list_PartNo": "291004114",
                "parts_list_PartNo_RefNo": "76",
                "parts_list_RefNo": "76",
                "parts_list_descrip": "291004114LH FRONT FOOT PAD",
                "parts_list_SalePrice": "47.99",
                "parts_list_QtyReq": "1",
                "image_main": "https://images.imagessite.com/OEM_IMAGES/seadoo_images/SD1584EA05.gif"
            },
            {
                "parts_list_HLSM_PartNo": "109628816",
                "parts_list_PartNo": "291004115",
                "parts_list_PartNo_RefNo": "77",
                "parts_list_RefNo": "77",
                "parts_list_descrip": "291004115RH FRONT BALLOON SLIDE RAIL",
                "parts_list_SalePrice": "109.99",
                "parts_list_QtyReq": "1",
                "image_main": "https://images.imagessite.com/OEM_IMAGES/seadoo_images/SD1584EA05.gif"
            },
            {
                "parts_list_HLSM_PartNo": "109628817",
                "parts_list_PartNo": "291004116",
                "parts_list_PartNo_RefNo": "78",
                "parts_list_RefNo": "78",
                "parts_list_descrip": "291004116LH FRONT BALLOON SLIDE RAIL",
                "parts_list_SalePrice": "109.99",
                "parts_list_QtyReq": "1",
                "image_main": "https://images.imagessite.com/OEM_IMAGES/seadoo_images/SD1584EA05.gif"
            },
            {
                "parts_list_HLSM_PartNo": "109628818",
                "parts_list_PartNo": "291004118",
                "parts_list_PartNo_RefNo": "79",
                "parts_list_RefNo": "79",
                "parts_list_descrip": "291004118RH FLOORBOARD",
                "parts_list_SalePrice": "889.99",
                "parts_list_QtyReq": "1",
                "image_main": "https://images.imagessite.com/OEM_IMAGES/seadoo_images/SD1584EA05.gif"
            },
            {
                "parts_list_HLSM_PartNo": "109628819",
                "parts_list_PartNo": "291004119",
                "parts_list_PartNo_RefNo": "80",
                "parts_list_RefNo": "80",
                "parts_list_descrip": "291004119LH FLOORBOARD",
                "parts_list_SalePrice": "889.99",
                "parts_list_QtyReq": "1",
                "image_main": "https://images.imagessite.com/OEM_IMAGES/seadoo_images/SD1584EA05.gif"
            },
            {
                "parts_list_HLSM_PartNo": "109628820",
                "parts_list_PartNo": "291004128",
                "parts_list_PartNo_RefNo": "81",
                "parts_list_RefNo": "81",
                "parts_list_descrip": "291004128PAD FOAM",
                "parts_list_SalePrice": "104.99",
                "parts_list_QtyReq": "1",
                "image_main": "https://images.imagessite.com/OEM_IMAGES/seadoo_images/SD1584EA05.gif"
            },
            {
                "parts_list_HLSM_PartNo": "109628825",
                "parts_list_PartNo": "291004151",
                "parts_list_PartNo_RefNo": "82",
                "parts_list_RefNo": "82",
                "parts_list_descrip": "291004151FRONT BALLOON SUPPORT (SMALL)",
                "parts_list_SalePrice": "0.00",
                "parts_list_QtyReq": "2",
                "image_main": "https://images.imagessite.com/OEM_IMAGES/seadoo_images/SD1584EA05.gif"
            },
            {
                "parts_list_HLSM_PartNo": "109628830",
                "parts_list_PartNo": "291004160",
                "parts_list_PartNo_RefNo": "83",
                "parts_list_RefNo": "83",
                "parts_list_descrip": "291004160BUMPER SUPPORT MA",
                "parts_list_SalePrice": "18.99",
                "parts_list_QtyReq": "1",
                "image_main": "https://images.imagessite.com/OEM_IMAGES/seadoo_images/SD1584EA05.gif"
            },
            {
                "parts_list_HLSM_PartNo": "109628832",
                "parts_list_PartNo": "291004166",
                "parts_list_PartNo_RefNo": "84",
                "parts_list_RefNo": "84",
                "parts_list_descrip": "291004166AIR PUMP ADAPTOR",
                "parts_list_SalePrice": "0.00",
                "parts_list_QtyReq": "1",
                "image_main": "https://images.imagessite.com/OEM_IMAGES/seadoo_images/SD1584EA05.gif"
            },
            {
                "parts_list_HLSM_PartNo": "109628833",
                "parts_list_PartNo": "291004167",
                "parts_list_PartNo_RefNo": "85",
                "parts_list_RefNo": "85",
                "parts_list_descrip": "291004167SHACKLE",
                "parts_list_SalePrice": "14.99",
                "parts_list_QtyReq": "8",
                "image_main": "https://images.imagessite.com/OEM_IMAGES/seadoo_images/SD1584EA05.gif"
            },
            {
                "parts_list_HLSM_PartNo": "109628839",
                "parts_list_PartNo": "291004187",
                "parts_list_PartNo_RefNo": "87",
                "parts_list_RefNo": "87",
                "parts_list_descrip": "291004187MID BALLOON SUPPORT (SMALL)",
                "parts_list_SalePrice": "0.00",
                "parts_list_QtyReq": "2",
                "image_main": "https://images.imagessite.com/OEM_IMAGES/seadoo_images/SD1584EA05.gif"
            },
            {
                "parts_list_HLSM_PartNo": "109628848",
                "parts_list_PartNo": "291004213",
                "parts_list_PartNo_RefNo": "88",
                "parts_list_RefNo": "88",
                "parts_list_descrip": "291004213APPUI CIVIRE",
                "parts_list_SalePrice": "0.00",
                "parts_list_QtyReq": "1",
                "image_main": "https://images.imagessite.com/OEM_IMAGES/seadoo_images/SD1584EA05.gif"
            },
            {
                "parts_list_HLSM_PartNo": "109628849",
                "parts_list_PartNo": "291004214",
                "parts_list_PartNo_RefNo": "89",
                "parts_list_RefNo": "89",
                "parts_list_descrip": "291004214SPRING PIN M4 X 50",
                "parts_list_SalePrice": "2.09",
                "parts_list_QtyReq": "1",
                "image_main": "https://images.imagessite.com/OEM_IMAGES/seadoo_images/SD1584EA05.gif"
            },
            {
                "parts_list_HLSM_PartNo": "109628850",
                "parts_list_PartNo": "291004219",
                "parts_list_PartNo_RefNo": "90",
                "parts_list_RefNo": "90",
                "parts_list_descrip": "291004219SHACKLE SPACER BUSHING",
                "parts_list_SalePrice": "17.49",
                "parts_list_QtyReq": "8",
                "image_main": "https://images.imagessite.com/OEM_IMAGES/seadoo_images/SD1584EA05.gif"
            },
            {
                "parts_list_HLSM_PartNo": "109629761",
                "parts_list_PartNo": "292000933",
                "parts_list_PartNo_RefNo": "91",
                "parts_list_RefNo": "91",
                "parts_list_descrip": "292000933U-CLAMP",
                "parts_list_SalePrice": "104.99",
                "parts_list_QtyReq": "1",
                "image_main": "https://images.imagessite.com/OEM_IMAGES/seadoo_images/SD1584EA05.gif"
            },
            {
                "parts_list_HLSM_PartNo": "109630087",
                "parts_list_PartNo": "293050001",
                "parts_list_PartNo_RefNo": "92",
                "parts_list_RefNo": "92",
                "parts_list_descrip": "293050001FLAT WASHER",
                "parts_list_SalePrice": "2.89",
                "parts_list_QtyReq": "2",
                "image_main": "https://images.imagessite.com/OEM_IMAGES/seadoo_images/SD1584EA05.gif"
            },
            {
                "parts_list_HLSM_PartNo": "109630157",
                "parts_list_PartNo": "293150186",
                "parts_list_PartNo_RefNo": "93",
                "parts_list_RefNo": "93",
                "parts_list_descrip": "293150186POP RIVET 3/16",
                "parts_list_SalePrice": "1.99",
                "parts_list_QtyReq": "32",
                "image_main": "https://images.imagessite.com/OEM_IMAGES/seadoo_images/SD1584EA05.gif"
            },
            {
                "parts_list_HLSM_PartNo": "109630330",
                "parts_list_PartNo": "293250218",
                "parts_list_PartNo_RefNo": "94",
                "parts_list_RefNo": "94",
                "parts_list_descrip": "293250218GASKET",
                "parts_list_SalePrice": "0.00",
                "parts_list_QtyReq": "1",
                "image_main": "https://images.imagessite.com/OEM_IMAGES/seadoo_images/SD1584EA05.gif"
            },
            {
                "parts_list_HLSM_PartNo": "109630926",
                "parts_list_PartNo": "293730006",
                "parts_list_PartNo_RefNo": "98",
                "parts_list_RefNo": "98",
                "parts_list_descrip": "293730006BLACK DART",
                "parts_list_SalePrice": "0.98",
                "parts_list_QtyReq": "8",
                "image_main": "https://images.imagessite.com/OEM_IMAGES/seadoo_images/SD1584EA05.gif"
            }
        ]
    },
    {
        "name": "BODY - HULL VIEW",
        "link": "https://onlinemicrofiche.com/riva_normal/showmodel/13/seadoopwc/492/6",
        "full_name": "2015 Sea Doo PWC SAR 155 WHITE/YELLOW - BODY - HULL VIEW",
        "image_src": "https://images.imagessite.com/OEM_IMAGES/seadoo_images_small/SD1584EA06.gif",
        "nameChildren": "BODY - HULL VIEW",
        "breadcrumb_menu": "Sea Doo /  PWC  /  2015",
        "model": "2015 SAR 155 WHITE/YELLOW",
        "infor": [
            {
                "parts_list_HLSM_PartNo": "10966826",
                "parts_list_PartNo": "205364060",
                "parts_list_PartNo_RefNo": "1",
                "parts_list_RefNo": "1",
                "parts_list_descrip": "205364060SOCKET HEAD SCREW M6 X 40",
                "parts_list_SalePrice": "1.79",
                "parts_list_QtyReq": "8",
                "image_main": "https://images.imagessite.com/OEM_IMAGES/seadoo_images/SD1584EA06.gif"
            },
            {
                "parts_list_HLSM_PartNo": "10966900",
                "parts_list_PartNo": "205562560",
                "parts_list_PartNo_RefNo": "2",
                "parts_list_RefNo": "2",
                "parts_list_descrip": "205562560SOCKET HEAD SCREW M6 X 25, SCOTCH GRIP",
                "parts_list_SalePrice": "1.99",
                "parts_list_QtyReq": "4",
                "image_main": "https://images.imagessite.com/OEM_IMAGES/seadoo_images/SD1584EA06.gif"
            },
            {
                "parts_list_HLSM_PartNo": "109612823",
                "parts_list_PartNo": "232561200",
                "parts_list_PartNo_RefNo": "3",
                "parts_list_RefNo": "3",
                "parts_list_descrip": "232561200ELASTIC STOP NUT M6, BRASS",
                "parts_list_SalePrice": "3.99",
                "parts_list_QtyReq": "32",
                "image_main": "https://images.imagessite.com/OEM_IMAGES/seadoo_images/SD1584EA06.gif"
            },
            {
                "parts_list_HLSM_PartNo": "109612830",
                "parts_list_PartNo": "232581200",
                "parts_list_PartNo_RefNo": "4",
                "parts_list_RefNo": "4",
                "parts_list_descrip": "232581200HEX. ELASTIC NUT M8, BRASS",
                "parts_list_SalePrice": "2.09",
                "parts_list_QtyReq": "8",
                "image_main": "https://images.imagessite.com/OEM_IMAGES/seadoo_images/SD1584EA06.gif"
            },
            {
                "parts_list_HLSM_PartNo": "109612923",
                "parts_list_PartNo": "234061600",
                "parts_list_PartNo_RefNo": "5",
                "parts_list_RefNo": "5",
                "parts_list_descrip": "234061600FLAT WASHER M6, STAINLESS",
                "parts_list_SalePrice": "0.31",
                "parts_list_QtyReq": "8",
                "image_main": "https://images.imagessite.com/OEM_IMAGES/seadoo_images/SD1584EA06.gif"
            },
            {
                "parts_list_HLSM_PartNo": "109612928",
                "parts_list_PartNo": "234062600",
                "parts_list_PartNo_RefNo": "6",
                "parts_list_RefNo": "6",
                "parts_list_descrip": "234062600FLAT WASHER M6, STAINLESS",
                "parts_list_SalePrice": "0.73",
                "parts_list_QtyReq": "28",
                "image_main": "https://images.imagessite.com/OEM_IMAGES/seadoo_images/SD1584EA06.gif"
            },
            {
                "parts_list_HLSM_PartNo": "109624245",
                "parts_list_PartNo": "279000164",
                "parts_list_PartNo_RefNo": "7",
                "parts_list_RefNo": "7",
                "parts_list_descrip": "279000164FLAT WASHER",
                "parts_list_SalePrice": "9.69",
                "parts_list_QtyReq": "2",
                "image_main": "https://images.imagessite.com/OEM_IMAGES/seadoo_images/SD1584EA06.gif"
            },
            {
                "parts_list_HLSM_PartNo": "109613313",
                "parts_list_PartNo": "250000572",
                "parts_list_PartNo_RefNo": "8",
                "parts_list_RefNo": "8",
                "parts_list_descrip": "250000572TORX-HEAD SCREW M8 X 35",
                "parts_list_SalePrice": "4.19",
                "parts_list_QtyReq": "4",
                "image_main": "https://images.imagessite.com/OEM_IMAGES/seadoo_images/SD1584EA06.gif"
            },
            {
                "parts_list_HLSM_PartNo": "109613416",
                "parts_list_PartNo": "250000744",
                "parts_list_PartNo_RefNo": "9",
                "parts_list_RefNo": "9",
                "parts_list_descrip": "250000744TORX SCEW M6 X 30",
                "parts_list_SalePrice": "1.89",
                "parts_list_QtyReq": "20",
                "image_main": "https://images.imagessite.com/OEM_IMAGES/seadoo_images/SD1584EA06.gif"
            },
            {
                "parts_list_HLSM_PartNo": "109613800",
                "parts_list_PartNo": "250200011",
                "parts_list_PartNo_RefNo": "10",
                "parts_list_RefNo": "10",
                "parts_list_descrip": "250200011FLAT WASHER 8 MM, STAINLESS",
                "parts_list_SalePrice": "2.89",
                "parts_list_QtyReq": "8",
                "image_main": "https://images.imagessite.com/OEM_IMAGES/seadoo_images/SD1584EA06.gif"
            },
            {
                "parts_list_HLSM_PartNo": "109629761",
                "parts_list_PartNo": "292000933",
                "parts_list_PartNo_RefNo": "12",
                "parts_list_RefNo": "12",
                "parts_list_descrip": "292000933U-CLAMP",
                "parts_list_SalePrice": "104.99",
                "parts_list_QtyReq": "1",
                "image_main": "https://images.imagessite.com/OEM_IMAGES/seadoo_images/SD1584EA06.gif"
            },
            {
                "parts_list_HLSM_PartNo": "109629832",
                "parts_list_PartNo": "292001471",
                "parts_list_PartNo_RefNo": "13",
                "parts_list_RefNo": "13",
                "parts_list_descrip": "292001471SQUARE HEAD STUD",
                "parts_list_SalePrice": "13.49",
                "parts_list_QtyReq": "6",
                "image_main": "https://images.imagessite.com/OEM_IMAGES/seadoo_images/SD1584EA06.gif"
            },
            {
                "parts_list_HLSM_PartNo": "109629839",
                "parts_list_PartNo": "292001503",
                "parts_list_PartNo_RefNo": "14",
                "parts_list_RefNo": "14",
                "parts_list_descrip": "292001503PUSH NUT",
                "parts_list_SalePrice": "1.19",
                "parts_list_QtyReq": "6",
                "image_main": "https://images.imagessite.com/OEM_IMAGES/seadoo_images/SD1584EA06.gif"
            },
            {
                "parts_list_HLSM_PartNo": "109629885",
                "parts_list_PartNo": "292001889",
                "parts_list_PartNo_RefNo": "15",
                "parts_list_RefNo": "15",
                "parts_list_descrip": "292001889ALUMINIUM RAIL",
                "parts_list_SalePrice": "109.99",
                "parts_list_QtyReq": "2",
                "image_main": "https://images.imagessite.com/OEM_IMAGES/seadoo_images/SD1584EA06.gif"
            },
            {
                "parts_list_HLSM_PartNo": "109629857",
                "parts_list_PartNo": "292001663",
                "parts_list_PartNo_RefNo": "17",
                "parts_list_RefNo": "17",
                "parts_list_descrip": "292001663FLAT WASHER 8 MM, NYLON",
                "parts_list_SalePrice": "1.29",
                "parts_list_QtyReq": "2",
                "image_main": "https://images.imagessite.com/OEM_IMAGES/seadoo_images/SD1584EA06.gif"
            },
            {
                "parts_list_HLSM_PartNo": "109629858",
                "parts_list_PartNo": "292001668",
                "parts_list_PartNo_RefNo": "18",
                "parts_list_RefNo": "18",
                "parts_list_descrip": "292001668RAIL SPACER",
                "parts_list_SalePrice": "149.99",
                "parts_list_QtyReq": "2",
                "image_main": "https://images.imagessite.com/OEM_IMAGES/seadoo_images/SD1584EA06.gif"
            },
            {
                "parts_list_HLSM_PartNo": "109629811",
                "parts_list_PartNo": "292001426",
                "parts_list_PartNo_RefNo": "21",
                "parts_list_RefNo": "21",
                "parts_list_descrip": "292001426RH SPONSON",
                "parts_list_SalePrice": "83.99",
                "parts_list_QtyReq": "1",
                "image_main": "https://images.imagessite.com/OEM_IMAGES/seadoo_images/SD1584EA06.gif"
            },
            {
                "parts_list_HLSM_PartNo": "109629812",
                "parts_list_PartNo": "292001427",
                "parts_list_PartNo_RefNo": "21",
                "parts_list_RefNo": "21",
                "parts_list_descrip": "292001427LH SPONSON",
                "parts_list_SalePrice": "83.99",
                "parts_list_QtyReq": "1",
                "image_main": "https://images.imagessite.com/OEM_IMAGES/seadoo_images/SD1584EA06.gif"
            },
            {
                "parts_list_HLSM_PartNo": "109629813",
                "parts_list_PartNo": "292001428",
                "parts_list_PartNo_RefNo": "22",
                "parts_list_RefNo": "22",
                "parts_list_descrip": "292001428RH STABILIZER SPACER",
                "parts_list_SalePrice": "35.99",
                "parts_list_QtyReq": "1",
                "image_main": "https://images.imagessite.com/OEM_IMAGES/seadoo_images/SD1584EA06.gif"
            },
            {
                "parts_list_HLSM_PartNo": "109629814",
                "parts_list_PartNo": "292001429",
                "parts_list_PartNo_RefNo": "22",
                "parts_list_RefNo": "22",
                "parts_list_descrip": "292001429LH STABILIZER SPACER",
                "parts_list_SalePrice": "47.99",
                "parts_list_QtyReq": "1",
                "image_main": "https://images.imagessite.com/OEM_IMAGES/seadoo_images/SD1584EA06.gif"
            },
            {
                "parts_list_HLSM_PartNo": "109629863",
                "parts_list_PartNo": "292001743",
                "parts_list_PartNo_RefNo": "23",
                "parts_list_RefNo": "23",
                "parts_list_descrip": "292001743PROTECTOR",
                "parts_list_SalePrice": "22.49",
                "parts_list_QtyReq": "1",
                "image_main": "https://images.imagessite.com/OEM_IMAGES/seadoo_images/SD1584EA06.gif"
            },
            {
                "parts_list_HLSM_PartNo": "109629864",
                "parts_list_PartNo": "292001775",
                "parts_list_PartNo_RefNo": "25",
                "parts_list_RefNo": "25",
                "parts_list_descrip": "292001775RH RAIL",
                "parts_list_SalePrice": "109.99",
                "parts_list_QtyReq": "1",
                "image_main": "https://images.imagessite.com/OEM_IMAGES/seadoo_images/SD1584EA06.gif"
            },
            {
                "parts_list_HLSM_PartNo": "109629865",
                "parts_list_PartNo": "292001798",
                "parts_list_PartNo_RefNo": "25",
                "parts_list_RefNo": "25",
                "parts_list_descrip": "292001798LH RAIL",
                "parts_list_SalePrice": "109.99",
                "parts_list_QtyReq": "1",
                "image_main": "https://images.imagessite.com/OEM_IMAGES/seadoo_images/SD1584EA06.gif"
            },
            {
                "parts_list_HLSM_PartNo": "109629866",
                "parts_list_PartNo": "292001804",
                "parts_list_PartNo_RefNo": "26",
                "parts_list_RefNo": "26",
                "parts_list_descrip": "292001804SPONSON PLATE",
                "parts_list_SalePrice": "49.99",
                "parts_list_QtyReq": "2",
                "image_main": "https://images.imagessite.com/OEM_IMAGES/seadoo_images/SD1584EA06.gif"
            },
            {
                "parts_list_HLSM_PartNo": "109629867",
                "parts_list_PartNo": "292001805",
                "parts_list_PartNo_RefNo": "27",
                "parts_list_RefNo": "27",
                "parts_list_descrip": "292001805SPONSON PLATE",
                "parts_list_SalePrice": "49.99",
                "parts_list_QtyReq": "2",
                "image_main": "https://images.imagessite.com/OEM_IMAGES/seadoo_images/SD1584EA06.gif"
            },
            {
                "parts_list_HLSM_PartNo": "109629872",
                "parts_list_PartNo": "292001836",
                "parts_list_PartNo_RefNo": "28",
                "parts_list_RefNo": "28",
                "parts_list_descrip": "292001836HEAT EXCHANGER SUPPORT",
                "parts_list_SalePrice": "73.99",
                "parts_list_QtyReq": "1",
                "image_main": "https://images.imagessite.com/OEM_IMAGES/seadoo_images/SD1584EA06.gif"
            },
            {
                "parts_list_HLSM_PartNo": "109631042",
                "parts_list_PartNo": "293830037",
                "parts_list_PartNo_RefNo": "32",
                "parts_list_RefNo": "32",
                "parts_list_descrip": "293830037RUBBER WASHER",
                "parts_list_SalePrice": "2.29",
                "parts_list_QtyReq": "2",
                "image_main": "https://images.imagessite.com/OEM_IMAGES/seadoo_images/SD1584EA06.gif"
            },
            {
                "parts_list_HLSM_PartNo": "109629859",
                "parts_list_PartNo": "292001738",
                "parts_list_PartNo_RefNo": "38",
                "parts_list_RefNo": "38",
                "parts_list_descrip": "292001738RH SPONSON",
                "parts_list_SalePrice": "204.99",
                "parts_list_QtyReq": "1",
                "image_main": "https://images.imagessite.com/OEM_IMAGES/seadoo_images/SD1584EA06.gif"
            },
            {
                "parts_list_HLSM_PartNo": "109629860",
                "parts_list_PartNo": "292001739",
                "parts_list_PartNo_RefNo": "38",
                "parts_list_RefNo": "38",
                "parts_list_descrip": "292001739LH SPONSON",
                "parts_list_SalePrice": "114.99",
                "parts_list_QtyReq": "1",
                "image_main": "https://images.imagessite.com/OEM_IMAGES/seadoo_images/SD1584EA06.gif"
            }
        ]
    },
    {
        "name": "SEAT",
        "link": "https://onlinemicrofiche.com/riva_normal/showmodel/13/seadoopwc/492/7",
        "full_name": "2015 Sea Doo PWC SAR 155 WHITE/YELLOW - SEAT",
        "image_src": "https://images.imagessite.com/OEM_IMAGES/seadoo_images_small/SD1584EA07.gif",
        "nameChildren": "SEAT",
        "breadcrumb_menu": "Sea Doo /  PWC  /  2015",
        "model": "2015 SAR 155 WHITE/YELLOW",
        "infor": [
            {
                "parts_list_HLSM_PartNo": "109612923",
                "parts_list_PartNo": "234061600",
                "parts_list_PartNo_RefNo": "5",
                "parts_list_RefNo": "5",
                "parts_list_descrip": "234061600FLAT WASHER M6, STAINLESS",
                "parts_list_SalePrice": "0.31",
                "parts_list_QtyReq": "2",
                "image_main": "https://images.imagessite.com/OEM_IMAGES/seadoo_images/SD1584EA07.gif"
            },
            {
                "parts_list_HLSM_PartNo": "109615604",
                "parts_list_PartNo": "269002087",
                "parts_list_PartNo_RefNo": "12",
                "parts_list_RefNo": "12",
                "parts_list_descrip": "269002087SEAT STRAP",
                "parts_list_SalePrice": "32.99",
                "parts_list_QtyReq": "1",
                "image_main": "https://images.imagessite.com/OEM_IMAGES/seadoo_images/SD1584EA07.gif"
            },
            {
                "parts_list_HLSM_PartNo": "109615504",
                "parts_list_PartNo": "269001937",
                "parts_list_PartNo_RefNo": "13",
                "parts_list_RefNo": "13",
                "parts_list_descrip": "269001937LH SEAT PROTECTOR",
                "parts_list_SalePrice": "7.29",
                "parts_list_QtyReq": "1",
                "image_main": "https://images.imagessite.com/OEM_IMAGES/seadoo_images/SD1584EA07.gif"
            },
            {
                "parts_list_HLSM_PartNo": "109615556",
                "parts_list_PartNo": "269001994",
                "parts_list_PartNo_RefNo": "14",
                "parts_list_RefNo": "14",
                "parts_list_descrip": "269001994RH SEAT PROTECTOR",
                "parts_list_SalePrice": "7.29",
                "parts_list_QtyReq": "1",
                "image_main": "https://images.imagessite.com/OEM_IMAGES/seadoo_images/SD1584EA07.gif"
            },
            {
                "parts_list_HLSM_PartNo": "109615653",
                "parts_list_PartNo": "269002151",
                "parts_list_PartNo_RefNo": "16",
                "parts_list_RefNo": "16",
                "parts_list_descrip": "269002151SEAT RECEPTACLE",
                "parts_list_SalePrice": "12.99",
                "parts_list_QtyReq": "1",
                "image_main": "https://images.imagessite.com/OEM_IMAGES/seadoo_images/SD1584EA07.gif"
            },
            {
                "parts_list_HLSM_PartNo": "109615989",
                "parts_list_PartNo": "269002803",
                "parts_list_PartNo_RefNo": "23",
                "parts_list_RefNo": "23",
                "parts_list_descrip": "269002803SEAT ASS'Y",
                "parts_list_SalePrice": "669.99",
                "parts_list_QtyReq": "1",
                "image_main": "https://images.imagessite.com/OEM_IMAGES/seadoo_images/SD1584EA07.gif"
            },
            {
                "parts_list_HLSM_PartNo": "109617475",
                "parts_list_PartNo": "269700109",
                "parts_list_PartNo_RefNo": "27",
                "parts_list_RefNo": "27",
                "parts_list_descrip": "269700109LATCH ASS'Y",
                "parts_list_SalePrice": "21.99",
                "parts_list_QtyReq": "1",
                "image_main": "https://images.imagessite.com/OEM_IMAGES/seadoo_images/SD1584EA07.gif"
            },
            {
                "parts_list_HLSM_PartNo": "109630135",
                "parts_list_PartNo": "293150067",
                "parts_list_PartNo_RefNo": "33",
                "parts_list_RefNo": "33",
                "parts_list_descrip": "293150067RIVET",
                "parts_list_SalePrice": "2.79",
                "parts_list_QtyReq": "2",
                "image_main": "https://images.imagessite.com/OEM_IMAGES/seadoo_images/SD1584EA07.gif"
            },
            {
                "parts_list_HLSM_PartNo": "109630149",
                "parts_list_PartNo": "293150123",
                "parts_list_PartNo_RefNo": "35",
                "parts_list_RefNo": "35",
                "parts_list_descrip": "293150123POP RIVET 3/16\"",
                "parts_list_SalePrice": "4.29",
                "parts_list_QtyReq": "6",
                "image_main": "https://images.imagessite.com/OEM_IMAGES/seadoo_images/SD1584EA07.gif"
            },
            {
                "parts_list_HLSM_PartNo": "109630151",
                "parts_list_PartNo": "293150151",
                "parts_list_PartNo_RefNo": "37",
                "parts_list_RefNo": "37",
                "parts_list_descrip": "293150151RIVET 1/4\"",
                "parts_list_SalePrice": "7.39",
                "parts_list_QtyReq": "2",
                "image_main": "https://images.imagessite.com/OEM_IMAGES/seadoo_images/SD1584EA07.gif"
            },
            {
                "parts_list_HLSM_PartNo": "109630905",
                "parts_list_PartNo": "293720067",
                "parts_list_PartNo_RefNo": "41",
                "parts_list_RefNo": "41",
                "parts_list_descrip": "293720067GROMMET",
                "parts_list_SalePrice": "11.49",
                "parts_list_QtyReq": "2",
                "image_main": "https://images.imagessite.com/OEM_IMAGES/seadoo_images/SD1584EA07.gif"
            }
        ]
    }
]